gretel_client/__init__.py
gretel_client/analysis_utils.py
gretel_client/bigquery.py
gretel_client/config.py
gretel_client/dataframe.py
gretel_client/errors.py
gretel_client/factories.py
gretel_client/helpers.py
gretel_client/navigator_client.py
gretel_client/navigator_client_protocols.py
gretel_client/readers.py
gretel_client/test_utils.py
gretel_client/_api/__init__.py
gretel_client/_api/api_client.py
gretel_client/_api/api_response.py
gretel_client/_api/configuration.py
gretel_client/_api/exceptions.py
gretel_client/_api/rest.py
gretel_client/_api/api/__init__.py
gretel_client/_api/api/files_api.py
gretel_client/_api/api/workflows_api.py
gretel_client/_api/models/__init__.py
gretel_client/_api/models/compile_workflow_config_request.py
gretel_client/_api/models/compile_workflow_config_response.py
gretel_client/_api/models/distribution_type.py
gretel_client/_api/models/exec_batch_request.py
gretel_client/_api/models/exec_batch_response.py
gretel_client/_api/models/exec_batch_retry_request.py
gretel_client/_api/models/file.py
gretel_client/_api/models/file_delete_response.py
gretel_client/_api/models/generation_parameters_input.py
gretel_client/_api/models/generation_parameters_output.py
gretel_client/_api/models/get_model_suites_response.py
gretel_client/_api/models/globals_input.py
gretel_client/_api/models/http_validation_error.py
gretel_client/_api/models/llm_info.py
gretel_client/_api/models/llm_suite_config_with_generation_params.py
gretel_client/_api/models/manual_distribution.py
gretel_client/_api/models/manual_distribution_params.py
gretel_client/_api/models/model_config_input.py
gretel_client/_api/models/model_config_output.py
gretel_client/_api/models/source_config_type.py
gretel_client/_api/models/step.py
gretel_client/_api/models/task_envelope_for_validation.py
gretel_client/_api/models/task_input.py
gretel_client/_api/models/task_validation_result.py
gretel_client/_api/models/temperature.py
gretel_client/_api/models/top_p.py
gretel_client-0.30.1.dist-info/LICENSE
gretel_client-0.30.1.dist-info/METADATA
gretel_client-0.30.1.dist-info/WHEEL
gretel_client-0.30.1.dist-info/entry_points.txt
gretel_client-0.30.1.dist-info/top_level.txt
gretel_client-0.30.1.dist-info/RECORD
