Metadata-Version: 2.1
Name: gretel-client
Version: 0.30.1
Summary: Balance, anonymize, and share your data. With privacy guarantees.
Home-page: https://github.com/gretelai/gretel-python-client
Author: Gretel Labs, Inc.
Author-email: support@gretel.ai
Classifier: Programming Language :: Python :: 3
Classifier: License :: OSI Approved :: Apache Software License
Classifier: Operating System :: POSIX :: Linux
Classifier: Operating System :: MacOS
Classifier: Topic :: Scientific/Engineering :: Artificial Intelligence
Requires-Python: >=3.11
License-File: LICENSE
Requires-Dist: certifi>=2021.10.8
Requires-Dist: click<9,>=8.1.3
Requires-Dist: inflection==0.5.1
Requires-Dist: jinja2==3.1.6
Requires-Dist: networkx==3.0
Requires-Dist: numpy>=1.23.5
Requires-Dist: pandas>=1.1.0
Requires-Dist: pyarrow==19.0.1
Requires-Dist: pycryptodome<4,>=3.19
Requires-Dist: pydantic>=2
Requires-Dist: python-dateutil>=2.8.0
Requires-Dist: pyyaml>=6.0.1
Requires-Dist: requests<3,>=2.25
Requires-Dist: rich>=13.7
Requires-Dist: smart-open<8.0,>=2.1.0
Requires-Dist: tabulate>=0.8.9
Requires-Dist: tenacity>=8.2.2
Requires-Dist: tqdm<5.0,>=4.66
Requires-Dist: urllib3>=1.26.5
Provides-Extra: aws
Requires-Dist: boto3; extra == "aws"
Requires-Dist: smart-open[s3]; extra == "aws"
Provides-Extra: azure
Requires-Dist: smart-open[azure]; extra == "azure"
Requires-Dist: azure-identity; extra == "azure"
Requires-Dist: azure-keyvault; extra == "azure"
Provides-Extra: gcp
Requires-Dist: smart-open[gcs]; extra == "gcp"
Requires-Dist: google-cloud-kms; extra == "gcp"
Provides-Extra: test
Requires-Dist: faker==20.1.0; extra == "test"
Requires-Dist: flake8==4.0.1; extra == "test"
Requires-Dist: openai>=1.58.0; extra == "test"
Requires-Dist: pylint==3.3.1; extra == "test"
Requires-Dist: pytest-cov==2.11.1; extra == "test"
Requires-Dist: pytest==7.2.0; extra == "test"
Provides-Extra: tuner
Requires-Dist: optuna==3.2.0; extra == "tuner"
